intellect_core/core.py
intellect_core/dto/__init__.py
intellect_core/dto/dto.py
intellect_core/handler.py
intellect_core-0.2.3.dist-info/LICENSE
intellect_core-0.2.3.dist-info/METADATA
intellect_core-0.2.3.dist-info/WHEEL
intellect_core-0.2.3.dist-info/RECORD
