Metadata-Version: 2.1
Name: intellect-core
Version: 0.2.3
Summary: Модуль интеграции с Интеллект
Author: Mrkorogod
Requires-Python: >=3.10,<4.0
Classifier: Programming Language :: Python :: 3
Classifier: Programming Language :: Python :: 3.10
Classifier: Programming Language :: Python :: 3.11
